{
  "status": [
    "Mencabut UU - No. 13/1961 tentang Ketentuan-ketentan Pokok Kepolisian Negara",
    "Dicabut UU - No. 2/2002 tentang Kepolisian Negara Republik Indonesia"
  ],
  "topic": "Kepolisian Negara Republik Indonesia",
  "year": 1997,
  "number": 28,
  "perkara": [],
  "lembaranNegaraNumber": "81",
  "tambahanLembaranNegaraNumber": "3710",
  "peraturanPelaksanaan": [
    {
      "pasal": "10",
      "ayat": "2",
      "peraturan": "Keputusan Presiden No. 54/2001",
      "keterangan": "Organisasi dan Tata Kerja Kepolisian Republik Indonesia"
    },
    {
      "pasal": "14",
      "ayat": "2",
      "peraturan": "Peraturan Pemerintah No. 0/0",
      "keterangan": "-"
    },
    {
      "pasal": "15",
      "ayat": "3",
      "peraturan": "Lain - Lain No. Pol/02/XII/95/1995",
      "keterangan": "Juklap Kapolri No. Pol / 02 / XII / 95 tentang perijinan dan pemberitahuan kegiatan masyarakat"
    },
    {
      "pasal": "20",
      "ayat": "-",
      "peraturan": "Keputusan Panglima TNI No. 0/0",
      "keterangan": "-"
    },
    {
      "pasal": "24",
      "ayat": "2",
      "peraturan": "Keputusan Kepala Kepolisian RI No. Skep/213/VII/1985",
      "keterangan": "Skep/213/VII/1985 Tentang Kode Etik Profesi Kepolisian RI"
    },
    {
      "pasal": "25",
      "ayat": "2",
      "peraturan": "Keputusan Kepala Kepolisian RI No. 0/0",
      "keterangan": "-"
    },
    {
      "pasal": "26",
      "ayat": "4",
      "peraturan": "Keputusan Kepala Kepolisian RI No. 0/0",
      "keterangan": "-"
    },
    {
      "pasal": "27",
      "ayat": "2",
      "peraturan": "Peraturan Pemerintah No. 16/1960",
      "keterangan": "Permintaan dan Pelaksanaan Bantuan Militer"
    },
    {
      "pasal": "6",
      "ayat": "3",
      "peraturan": "Peraturan Pemerintah No. 0/0",
      "keterangan": "-"
    },
    {
      "pasal": "8",
      "ayat": "3",
      "peraturan": "Keputusan Presiden No. 89/2000",
      "keterangan": "Kedudukan Kepolisian Negara Republik Indonesia"
    },
    {
      "pasal": "9",
      "ayat": "4",
      "peraturan": "Keputusan Presiden No. 54/2001",
      "keterangan": "Organisasi dan Tata Kerja Kepolisian Republik Indonesia"
    }
  ]
}