{
  "status": [
    "Mencabut UU - UU No. 4/1950, UU No. 12/1954, UU NO. 22/1961, UU 14 Prps/1965, UU 19 Pnps/1965",
    "Dicabut UU - UU No. 20/2003"
  ],
  "topic": "Sistem Pendidikan Nasional",
  "year": 1989,
  "number": 2,
  "perkara": [],
  "lembaranNegaraNumber": "6",
  "tambahanLembaranNegaraNumber": "3390",
  "peraturanPelaksanaan": [
    {
      "pasal": "10",
      "ayat": "5",
      "peraturan": "Peraturan Pemerintah No. 73/1991",
      "keterangan": "Pendidikan Luar Sekolah"
    },
    {
      "pasal": "11",
      "ayat": "9",
      "peraturan": "Peraturan Pemerintah No. 27/1990",
      "keterangan": "Pendidikan Prasekolah"
    },
    {
      "pasal": "12",
      "ayat": "3",
      "peraturan": "Peraturan Pemerintah No. 27/1990",
      "keterangan": "Pendidikan Prasekolah"
    },
    {
      "pasal": "13",
      "ayat": "2",
      "peraturan": "Peraturan Pemerintah No. 28/1990",
      "keterangan": "Sekolah Dasar sebagaimana telah diubah dengan PP No. 55 Tahun 1998"
    },
    {
      "pasal": "14",
      "ayat": "3",
      "peraturan": "Peraturan Pemerintah No. 28/1990",
      "keterangan": "Sekolah Dasar sebagaimana telah diubah dengan PP No. 55 Tahun 1998"
    },
    {
      "pasal": "15",
      "ayat": "4",
      "peraturan": "Peraturan Pemerintah No. 29/1990",
      "keterangan": "Pendidikan Menengah sebagaimana telah diubah dengan PP No. 56 Tahun 1998"
    },
    {
      "pasal": "16",
      "ayat": "8",
      "peraturan": "Peraturan Pemerintah No. 60/1999",
      "keterangan": "Pendidikan Tinggi"
    },
    {
      "pasal": "18",
      "ayat": "6",
      "peraturan": "Peraturan Pemerintah No. 60/1999",
      "keterangan": "Pendidikan Tinggi"
    },
    {
      "pasal": "21",
      "ayat": "3",
      "peraturan": "Peraturan Pemerintah No. 60/1999",
      "keterangan": "Pendidikan Tinggi"
    },
    {
      "pasal": "22",
      "ayat": "3",
      "peraturan": "Peraturan Pemerintah No. 60/1999",
      "keterangan": "Pendidikan Tinggi"
    },
    {
      "pasal": "28",
      "ayat": "4",
      "peraturan": "Peraturan Pemerintah No. 38/1992",
      "keterangan": "Tenaga Pendidikan sebagaimana telah diubah dengan PP No. 39 Tahun 2000"
    },
    {
      "pasal": "29",
      "ayat": "2",
      "peraturan": "Peraturan Pemerintah No. 38/1992",
      "keterangan": "Tenaga Kependidikan sebagaimana telah diubah dengan PP No. 9 Tahun 2000"
    },
    {
      "pasal": "32",
      "ayat": "4",
      "peraturan": "Peraturan Pemerintah No. 38/1992",
      "keterangan": "Tenaga Kependidikan sebagaimana telah diubah dengan PP No. 39 Tahun 2000"
    },
    {
      "pasal": "47",
      "ayat": "3",
      "peraturan": "Peraturan Pemerintah No. 39/1992",
      "keterangan": "Peran Serta Masyarakat dalam Pendidikan Nasional"
    },
    {
      "pasal": "54",
      "ayat": "5",
      "peraturan": "Peraturan Pemerintah No. 27/1990",
      "keterangan": "Pendidikan Prasekolah"
    },
    {
      "pasal": "8",
      "ayat": "3",
      "peraturan": "Peraturan Pemerintah No. 72/1991",
      "keterangan": "Pendidikan Luar Biasa"
    }
  ]
}