{
  "status": [
    "Mengubah UU - UU No. 16/1969, UU No. 5/1975",
    "Diubah UU - UU No. 5/1995",
    "Dicabut UU - UU No. 4/1999"
  ],
  "topic": "Perubahan atas Undang-Undang Nomor 16 Tahun 1969 tentang Susunan dan Kedudukan Majelis Permusyawaratan Rakyat, Dewan Perwakilan Rakyat dan Dewan Perwakilan Rakyat Daerah Sebagaimana telah Diubah dengan Undang-Undang Nomor 5 Tahun 1975.",
  "year": 1985,
  "number": 2,
  "perkara": [],
  "lembaranNegaraNumber": "2",
  "tambahanLembaranNegaraNumber": "3282",
  "peraturanPelaksanaan": []
}