{
  "status": [
    "Diubah UU - No. 7/1985"
  ],
  "topic": "Anggaran Pendapatan dan Belanja Negara Tahun Anggaran 1984/1985",
  "year": 1984,
  "number": 1,
  "perkara": [],
  "lembaranNegaraNumber": "8",
  "tambahanLembaranNegaraNumber": "3268",
  "peraturanPelaksanaan": [
    {
      "pasal": "2",
      "ayat": "7",
      "peraturan": "Keputusan Presiden No. 54/1984",
      "keterangan": "Perincian Anggaran Belanja Rutin  Tahun Anggaran 1984/1985"
    },
    {
      "pasal": "2",
      "ayat": "6",
      "peraturan": "Keputusan Presiden No. 53/1984",
      "keterangan": "Perincian Sumber-Sumber Anggaran Rutin Dan Sumber-Sumber Anggaran Pembangunan Tahun Anggaran 1984/1985."
    },
    {
      "pasal": "4",
      "ayat": "1",
      "peraturan": "Peraturan Pemerintah No. 39/1985",
      "keterangan": "Pemindahan Sisa Anggaran Pembangunan Tahun Anggaran 1984/1985 Kepada Tahun Anggaran 1985/1986\n\n"
    }
  ]
}