{
  "status": [
    "Dicabut Putusan Mahkamah Konstitusi - No.007/PUU-III/2005, Pasal 5 ayat (2), ayat (3) dan ayat (4) bertentangan dan tidak mempunyai kekuatan hukum mengikat. ",
    "Dicabut Putusan Mahkamah Konstitusi - No.70/PUU-IX/2011, Pasal 4 ayat (1) UU No.3 Tahun 1992 tentang Jaminan Sosial Tenaga Kerja dan Pasal 13 ayat (1) UU No.40 tahun 2004 Tentang SJSN tidak mempunyai kekuatan hukum mengikat"
  ],
  "topic": "Sistem Jaminan Sosial Nasional",
  "year": 2004,
  "number": 40,
  "perkara": [
    "007/PUU-III/2005",
    "50/PUU-VIII/2010",
    "51/PUU-IX/2011",
    "70/PUU-IX/2011",
    "9/PUU-X/2012",
    "90/PUU-X/2012",
    "101/PUU-XI/2013"
  ],
  "lembaranNegaraNumber": "150",
  "tambahanLembaranNegaraNumber": "4456",
  "peraturanPelaksanaan": [
    {
      "pasal": "10",
      "ayat": "-",
      "peraturan": "Peraturan Presiden No. 46/2014",
      "keterangan": "Susunan Organisasi Dan Tata Kerja, Tata Cara Pengangkatan, Penggantian, Dan Pemberhentian Anggota Dewan Jaminan Sosial Nasional"
    },
    {
      "pasal": "12",
      "ayat": "2",
      "peraturan": "Peraturan Presiden No. 46/2014",
      "keterangan": "Susunan Organisasi Dan Tata Kerja, Tata Cara Pengangkatan, Penggantian, Dan Pemberhentian Anggota Dewan Jaminan Sosial Nasional"
    },
    {
      "pasal": "13",
      "ayat": "2",
      "peraturan": "Peraturan Presiden No. 109/2013",
      "keterangan": "Penahapan Kepesertaan Program Jaminan Sosial"
    },
    {
      "pasal": "14",
      "ayat": "3",
      "peraturan": "Peraturan Pemerintah No. 76/2015",
      "keterangan": "perubahan Atas Peraturan Pemerintah Nomor 101 Tahun 2012 Tentang Penerima Bantuan Iuran Jaminan Kesehatan"
    },
    {
      "pasal": "17",
      "ayat": "6",
      "peraturan": "Peraturan Pemerintah No. 76/2015",
      "keterangan": "perubahan Atas Peraturan Pemerintah Nomor 101 Tahun 2012 Tentang Penerima Bantuan Iuran Jaminan Kesehatan\n\n"
    },
    {
      "pasal": "21",
      "ayat": "4",
      "peraturan": "Peraturan Presiden No. 28/2016",
      "keterangan": "Perubahan Ketiga atas Peraturan Presiden Nomor 12 Tahun 2013 tentang Jaminan Kesehatan\n"
    },
    {
      "pasal": "22",
      "ayat": "3",
      "peraturan": "Peraturan Presiden No. 28/2016",
      "keterangan": "Perubahan Ketiga atas Peraturan Presiden Nomor 12 Tahun 2013 tentang Jaminan Kesehatan\n"
    },
    {
      "pasal": "23",
      "ayat": "5",
      "peraturan": "Peraturan Presiden No. 28/2016",
      "keterangan": "Perubahan Ketiga atas Peraturan Presiden Nomor 12 Tahun 2013 tentang Jaminan Kesehatan\n"
    },
    {
      "pasal": "26",
      "ayat": "0",
      "peraturan": "Peraturan Presiden No. 28/2016",
      "keterangan": "Perubahan Ketiga atas Peraturan Presiden Nomor 12 Tahun 2013 tentang Jaminan Kesehatan"
    },
    {
      "pasal": "27",
      "ayat": "5",
      "peraturan": "Peraturan Presiden No. 28/2016",
      "keterangan": "Perubahan Ketiga atas Peraturan Presiden Nomor 12 Tahun 2013 tentang Jaminan Kesehatan"
    },
    {
      "pasal": "28",
      "ayat": "2",
      "peraturan": "Peraturan Presiden No. 28/2016",
      "keterangan": "Perubahan Ketiga atas Peraturan Presiden Nomor 12 Tahun 2013 tentang Jaminan Kesehatan\n"
    },
    {
      "pasal": "33",
      "ayat": "0",
      "peraturan": "Peraturan Pemerintah No. 82/2019",
      "keterangan": "Perubahan Atas Peraturan Pemerintah Nomor 44 Tahun 2015 Tentang Penyelenggaraan Program Jaminan Kecelakaan Kerja Dan Jaminan Kematian"
    },
    {
      "pasal": "34",
      "ayat": "4",
      "peraturan": "Peraturan Pemerintah No. 82/2019",
      "keterangan": "Perubahan Atas Peraturan Pemerintah Nomor 44 Tahun 2015 Tentang Penyelenggaraan Program Jaminan Kecelakaan Kerja Dan Jaminan Kematian"
    },
    {
      "pasal": "37",
      "ayat": "5",
      "peraturan": "Peraturan Pemerintah No. 60/2015",
      "keterangan": "Tentang Perubahan atas Peraturan Pemerintah Nomor 46 Tahun 2015 tentang Penyelenggaraan Program Jaminan Hari Tua"
    },
    {
      "pasal": "38",
      "ayat": "3",
      "peraturan": "Peraturan Pemerintah No. 60/2015",
      "keterangan": "Tentang Perubahan atas Peraturan Pemerintah Nomor 46 Tahun 2015 tentang Penyelenggaraan Program Jaminan Hari Tua"
    },
    {
      "pasal": "41",
      "ayat": "8",
      "peraturan": "Peraturan Pemerintah No. 45/2015",
      "keterangan": "Penyelenggaraan Program Jaminan Pensiun"
    },
    {
      "pasal": "42",
      "ayat": "2",
      "peraturan": "Peraturan Pemerintah No. 45/2015",
      "keterangan": "Penyelenggaraan Program Jaminan Pensiun"
    },
    {
      "pasal": "45",
      "ayat": "3",
      "peraturan": "Peraturan Pemerintah No. 82/2019",
      "keterangan": "Perubahan Atas Peraturan Pemerintah Nomor 44 Tahun 2015 Tentang Penyelenggaraan Program Jaminan Kecelakaan Kerja Dan Jaminan Kematian"
    },
    {
      "pasal": "46",
      "ayat": "4",
      "peraturan": "Peraturan Pemerintah No. 82/2019",
      "keterangan": "Perubahan Atas Peraturan Pemerintah Nomor 44 Tahun 2015 Tentang Penyelenggaraan Program Jaminan Kecelakaan Kerja Dan Jaminan Kematian"
    },
    {
      "pasal": "47",
      "ayat": "2",
      "peraturan": "Peraturan Pemerintah No. 55/2015",
      "keterangan": "Perubahan Atas Peraturan Pemerintah Nomor 99 Tahun 2013 tentang Pengelolaan Aset Jaminan Sosial Ketenagakerjaan"
    },
    {
      "pasal": "50",
      "ayat": "2",
      "peraturan": "Peraturan Pemerintah No. 55/2015",
      "keterangan": "Perubahan Atas Peraturan Pemerintah Nomor 99 Tahun 2013 tentang Pengelolaan Aset Jaminan Sosial Ketenagakerjaan"
    }
  ]
}