{
  "status": [
    "Mencabut UU - Ketentuan mengenai tugas, wewenang dan kewajiban penyelenggara pemilihan gubernur, bupati, dan walikota  UU NO. 15/2011 tentang  Penyelenggara Pemilihan Umum. ",
    "Dicabut Peraturan Pemerintah Pengganti Undang-Undang - Perppu No.1 Tahun 2014"
  ],
  "topic": "Pemilihan Gubernur, Bupati, Dan Walikota ",
  "year": 2014,
  "number": 22,
  "perkara": [
    "97/PUU-XII/2014",
    "102/PUU-XII/2014",
    "98/PUU-XII/2014",
    "99/PUU-XII/2014",
    "103/PUU-XII/2014",
    "104/PUU-XII/2014",
    "105/PUU-XII/2014",
    "111/PUU-XII/2014"
  ],
  "lembaranNegaraNumber": "243",
  "tambahanLembaranNegaraNumber": "5586",
  "peraturanPelaksanaan": []
}