{
  "status": [
    "Mencabut UU - UU No. 24/1997 tentang Penyiaran ",
    "Dicabut Putusan Mahkamah Konstitusi - 005/PUU-I/2003, tanggal 25 Februari 2004 (untuk Pasal 44 ayat (1) dan Pasal 62 ayat (1) dan (2) )"
  ],
  "topic": "Penyiaran",
  "year": 2002,
  "number": 32,
  "perkara": [
    "005/PUU-I/2003",
    "031/PUU-IV/2006",
    "6/PUU-VII/2009",
    "78PUU-IX/2011",
    "71/PUU-XI/2013",
    "62/PUU-XIV/2016",
    "81/PUU-XIV/2017",
    "39/PUU-XVIII/2020"
  ],
  "lembaranNegaraNumber": "139",
  "tambahanLembaranNegaraNumber": "4252",
  "peraturanPelaksanaan": [
    {
      "pasal": "11",
      "ayat": "3",
      "peraturan": "Peraturan Komisi Penyiaran Indonesia No. 1/2014",
      "keterangan": "Kelembagaan Komisi Penyiaran Indonesia"
    },
    {
      "pasal": "12",
      "ayat": "-",
      "peraturan": "Peraturan Komisi Penyiaran Indonesia No. 1/2014",
      "keterangan": "Kelembagaan Komisi Penyiaran Indonesia"
    },
    {
      "pasal": "14",
      "ayat": "10",
      "peraturan": "Peraturan Pemerintah No. 13/2005",
      "keterangan": "Lembaga Penyiaran Publik Televisi Republik Indonesia"
    },
    {
      "pasal": "18",
      "ayat": "3",
      "peraturan": "Peraturan Pemerintah No. 50/2005",
      "keterangan": "Penyelenggaraan Penyiaran Lembaga Penyiaran Swasta sebagaimana telah diubah dengan PP No. 46 Tahun 2021 tentang Pos, Telekomunikasi dan Penyiaran."
    },
    {
      "pasal": "18",
      "ayat": "4",
      "peraturan": "Peraturan Pemerintah No. 52/2005",
      "keterangan": "Penyelenggaraan Penyiaran Lembaga Penyiaran Berlangga-nan sebagaimana telah diubah dengan PP No. 46 Tahun 2021 tentang Pos, Telekomunikasi dan Penyiaran."
    },
    {
      "pasal": "29",
      "ayat": "2",
      "peraturan": "Peraturan Pemerintah No. 52/2005",
      "keterangan": "Penyelenggaraan Penyiaraan Lembaga Penyiaran Berlangganan sebagaimana telah diubah dengan PP No. 46 Tahun 2021 tentang Pos, Telekomunikasi dan Penyiaran."
    },
    {
      "pasal": "30",
      "ayat": "3",
      "peraturan": "Peraturan Pemerintah No. 49/2005",
      "keterangan": "Pedoman Kegiatan Peliputan Lembaga Penyiaran Asing."
    },
    {
      "pasal": "31",
      "ayat": "4",
      "peraturan": "Peraturan Pemerintah No. 50/2005",
      "keterangan": "Penyelenggaraan Penyiaran Lembaga Penyiaran Swasta sebagaimana telah diubah dengan PP No. 46 Tahun 2021 tentang Pos, Telekomunikasi dan Penyiaran."
    },
    {
      "pasal": "32",
      "ayat": "2",
      "peraturan": "Peraturan Pemerintah No. 11/2005",
      "keterangan": "Penyelenggaraan Penyiaran Lembaga Penyiaran Publik sebagaimana telah diubah dengan PP No. 46 Tahun 2021 tentang Pos, Telekomunikasi dan Penyiaran "
    },
    {
      "pasal": "33",
      "ayat": "8",
      "peraturan": "Peraturan Pemerintah No. 11/2005",
      "keterangan": "Penyelenggaraan Penyiaran Lembaga Penyiaran Publik sebagaimana telah diubah dengan PP No. 46 Tahun 2021 tentang Pos, Telekomunikasi dan Penyiaran"
    },
    {
      "pasal": "55",
      "ayat": "3",
      "peraturan": "Peraturan Pemerintah No. 51/2005",
      "keterangan": "Penyelenggaraan Penyiaran Lembaga Penyiaran Komunitas sebagaimana telah diubah dengan PP No. 46 Tahun 2021 tentang Pos, Telekomunikasi dan Penyiaran"
    }
  ]
}