{
  "status": [
    "Menetapkan Peraturan Pemerintah Pengganti Undang-Undang - Perppu No. 2 Tahun 2020",
    "Mengubah UU - UU No. 1 Tahun 2015"
  ],
  "topic": "Penetapan Peraturan Pemerintah Pengganti Undang-Undang Nomor 2 Tahun 2020 Tentang Perubahan Ketiga Atas Undang-Undang Nomor 1 Tahun 2015 Tentang Penetapan Peraturan Pemerintah Pengganti Undang-Undang Nomor 1 Tahun 2014 Tentang Pemilihan Gubernur, Bupati, Dan Walikota Menjadi Undang-Undang Menjadi Undang-Undang",
  "year": 2020,
  "number": 6,
  "perkara": [],
  "lembaranNegaraNumber": "193",
  "tambahanLembaranNegaraNumber": "6547",
  "peraturanPelaksanaan": [
    {
      "pasal": "122A",
      "ayat": "3",
      "peraturan": "Peraturan Komisi Pemilihan Umum No. 6/2020",
      "keterangan": "Pelaksanaan Pemilihan Gubernur dan Wakil Gubernur, Bupati dan Wakil Bupati, dan/atau Wali Kota dan Wakil Wali Kota Serentak Lanjutan Dalam Kondisi Bencana NonAlam Corona Virus Disease 2019 (Covid-19)"
    }
  ]
}