{
  "status": [
    "Menetapkan Peraturan Pemerintah Pengganti Undang-Undang - Perpu No.1/2004 tentang Perubahan atas Undang - Undang Nomor 41 Tahun 1999 tentang Kehutanan Menjadi Undang - Undang",
    "Mengubah UU - UU NO. 41/1999 tentang Kehutanan"
  ],
  "topic": "Penetapan Peraturan Pemerintah Pengganti Undang - Undang Nomor 1 Tahun 2004 tentang Perubahan atas Undang - Undang Nomor 41 Tahun 1999 tentang Kehutanan Menjadi Undang - Undang.",
  "year": 2004,
  "number": 19,
  "perkara": [
    "003/PUU-III/2005",
    "72/PUU-VIII/2010"
  ],
  "lembaranNegaraNumber": "86",
  "tambahanLembaranNegaraNumber": "4412",
  "peraturanPelaksanaan": [
    {
      "pasal": "83",
      "ayat": "-",
      "peraturan": "Keputusan Presiden No. 41/2004",
      "keterangan": "PERIZINAN ATAU PERJANJIAN\nDI BIDANG PERTAMBANGAN YANG BERADA DI KAWASAN HUTAN\nPRESIDEN REPUBLIK INDONESIA,"
    }
  ]
}